fintoolkit/__init__.py
fintoolkit/compound_interest_calculator.py
fintoolkit/sip_calculator.py
pyfinops/__init__.py
pyfinops/compound_interest_calculator.py
pyfinops/scripts.py
pyfinops/sip_calculator.py
PyFinOps-0.3.2.dist-info/LICENSE
PyFinOps-0.3.2.dist-info/METADATA
PyFinOps-0.3.2.dist-info/WHEEL
PyFinOps-0.3.2.dist-info/entry_points.txt
PyFinOps-0.3.2.dist-info/top_level.txt
PyFinOps-0.3.2.dist-info/RECORD
