Metadata-Version: 2.1
Name: PyFinOps
Version: 0.3.2
Summary: A comprehensive toolkit for various financial calculations and tools.
Home-page: https://github.com/Anubhav9287/PyFinOps
Author: Anubhav Sharma
Author-email: anubhav9287@gmail.com
License: UNKNOWN
Platform: UNKNOWN
Classifier: Programming Language :: Python :: 3
Classifier: License :: OSI Approved :: MIT License
Classifier: Operating System :: OS Independent
Classifier: Topic :: Office/Business :: Financial :: Accounting
Classifier: Topic :: Software Development :: Libraries :: Python Modules
Requires-Python: >=3.6
